pyfs_base/__init__.py
pyfs_base/base.py
pyfs_base-1.0.4.dist-info/METADATA
pyfs_base-1.0.4.dist-info/WHEEL
pyfs_base-1.0.4.dist-info/top_level.txt
pyfs_base-1.0.4.dist-info/RECORD
